LICENSE
README.md
setup.py
offlinerllib/__init__.py
offlinerllib.egg-info/PKG-INFO
offlinerllib.egg-info/SOURCES.txt
offlinerllib.egg-info/dependency_links.txt
offlinerllib.egg-info/requires.txt
offlinerllib.egg-info/top_level.txt
offlinerllib/buffer/__init__.py
offlinerllib/buffer/base.py
offlinerllib/buffer/d4rl_buffer.py
offlinerllib/buffer/lap_buffer.py
offlinerllib/env/__init__.py
offlinerllib/env/d4rl.py
offlinerllib/env/mixed.py
offlinerllib/env/neorl_mujoco.py
offlinerllib/module/__init__.py
offlinerllib/module/actor.py
offlinerllib/module/critic.py
offlinerllib/module/td7_net.py
offlinerllib/module/net/__init__.py
offlinerllib/module/net/basic.py
offlinerllib/module/net/mlp.py
offlinerllib/module/net/attention/__init__.py
offlinerllib/module/net/attention/base.py
offlinerllib/module/net/attention/dt.py
offlinerllib/module/net/attention/gpt2.py
offlinerllib/module/net/attention/positional_encoding.py
offlinerllib/module/net/attention/transformer.py
offlinerllib/policy/__init__.py
offlinerllib/policy/base.py
offlinerllib/policy/model_free/__init__.py
offlinerllib/policy/model_free/awac.py
offlinerllib/policy/model_free/dt.py
offlinerllib/policy/model_free/edac.py
offlinerllib/policy/model_free/inac.py
offlinerllib/policy/model_free/iql.py
offlinerllib/policy/model_free/sac.py
offlinerllib/policy/model_free/sacn.py
offlinerllib/policy/model_free/td3.py
offlinerllib/policy/model_free/td3bc.py
offlinerllib/policy/model_free/td7.py
offlinerllib/policy/model_free/xql.py
offlinerllib/policy/model_free/xsac.py
offlinerllib/utils/__init__.py
offlinerllib/utils/d4rl.py
offlinerllib/utils/distributions.py
offlinerllib/utils/eval.py
offlinerllib/utils/functional.py
offlinerllib/utils/misc.py
offlinerllib/utils/noise.py
offlinerllib/utils/terminal.py