Metadata-Version: 2.1
Name: offlinerllib
Version: 0.1.5
Summary: A python module desgined for Offline RL algorithms developing and benchmarking. 
Home-page: https://github.com/typoverflow/OfflineRLLib
Author: typoverflow
Author-email: typoverflow@outlook.com
License: MIT
Requires-Python: >=3.7
License-File: LICENSE
Requires-Dist: gym<=0.24.1,>=0.23.1
Requires-Dist: tqdm
Requires-Dist: numpy
Requires-Dist: torch
Requires-Dist: pandas
Requires-Dist: UtilsRL
